<manifest alg="2" build="704" opt="false" iceEnabled="true">
  <folder name="css">
    <file name="site_global.css" crc="317297851"/>
    <file name="master_master.css" crc="342613112" ref="confirmation:kart-map:the-koffee:preparation:about:contact:orgins"/>
    <file name="master_masterflash.css" crc="453491898" ref="index"/>
    <file name="confirmation.css" crc="3849360844" ref="confirmation"/>
    <file name="kart-map.css" crc="4146492406" ref="kart-map"/>
    <file name="the-koffee.css" crc="155871827" ref="the-koffee"/>
    <file name="index.css" crc="36364632" ref="index"/>
    <file name="preparation.css" crc="108825844" ref="preparation"/>
    <file name="about.css" crc="318077495" ref="about"/>
    <file name="contact.css" crc="128999700" ref="contact"/>
    <file name="orgins.css" crc="132641500" ref="orgins"/>
  </folder>
  <folder name="scripts">
    <file name="jquery-1.8.3.min.js" crc="209076791" ref="index:the-koffee:kart-map:about:contact:preparation:orgins:confirmation"/>
    <file name="museutils.js" crc="3992981318" ref="index:the-koffee:kart-map:about:contact:preparation:orgins:confirmation"/>
    <file name="pie.js" crc="3827607177" ref="index:the-koffee:kart-map:about:contact:preparation:orgins:confirmation"/>
    <file name="jquery.musemenu.js" crc="3788803530" ref="index:the-koffee:kart-map:about:contact:preparation:orgins:confirmation"/>
    <file name="jquery.musepolyfill.bgsize.js" crc="3956991090" ref="index:the-koffee:kart-map:about:contact:preparation:orgins:confirmation"/>
    <file name="webpro.js" crc="197321703" ref="index:the-koffee:kart-map:about:contact:preparation:orgins:confirmation"/>
    <file name="musewpslideshow.js" crc="4283859919" ref="index:the-koffee:kart-map:about:contact:preparation:orgins:confirmation"/>
    <file name="jquery.museoverlay.js" crc="3836522771" ref="index:the-koffee:kart-map:about:contact:preparation:orgins:confirmation"/>
    <file name="touchswipe.js" crc="4156838003" ref="index:the-koffee:kart-map:about:contact:preparation:orgins:confirmation"/>
    <file name="jquery.tobrowserwidth.js" crc="317228635" ref="index:the-koffee:kart-map:about:contact:preparation:orgins:confirmation"/>
    <file name="musewpdisclosure.js" crc="4285748861" ref="the-koffee"/>
  </folder>
  <folder name="images">
    <file name="masterflash-favicon.ico" crc="4266726152" ref="index"/>
    <file name="bk-map.gif" crc="352965579" ref="index:the-koffee:kart-map:about:contact:preparation:orgins:confirmation"/>
    <file name="logo.swf" crc="165970871" ref="index"/>
    <file name="top-nav-u11899.png" crc="4277562052" ref="index"/>
    <file name="thedrip.png" crc="82547351" ref="index:the-koffee:kart-map:about:contact:preparation:orgins:confirmation"/>
    <file name="top-nav-over.png" crc="3906178592" ref="index:the-koffee:kart-map:about:contact:preparation:orgins:confirmation"/>
    <file name="arrowmenudown.gif" crc="213132104" ref="index:the-koffee:kart-map:about:contact:preparation:orgins:confirmation"/>
    <file name="btn_share.png" crc="3977030683" ref="index:the-koffee:kart-map:about:contact:preparation:orgins:confirmation"/>
    <file name="btn_share2.png" crc="65690245" ref="index:the-koffee:kart-map:about:contact:preparation:orgins:confirmation"/>
    <file name="btn_share3.png" crc="4204005391" ref="index:the-koffee:kart-map:about:contact:preparation:orgins:confirmation"/>
    <file name="gold-circle-twitter.png" crc="3852460767" ref="index:the-koffee:kart-map:about:contact:preparation:orgins:confirmation"/>
    <file name="gold-circle-facebook.png" crc="105570177" ref="index:the-koffee:kart-map:about:contact:preparation:orgins:confirmation"/>
    <file name="gold-circle-yelp.png" crc="492663769" ref="index:the-koffee:kart-map:about:contact:preparation:orgins:confirmation"/>
    <file name="gold-circle-foursquare.png" crc="264071105" ref="index:the-koffee:kart-map:about:contact:preparation:orgins:confirmation"/>
    <file name="acc-yellow.png" crc="24571853" ref="index:the-koffee:kart-map:about:contact:preparation:orgins:confirmation"/>
    <file name="koffeekart_hp_hero_05.jpg" crc="4139418258" ref="index"/>
    <file name="blank.gif" crc="4208392903" ref="index:orgins"/>
    <file name="koffeekart_hp_hero_01.jpg" crc="3968278864" ref="index"/>
    <file name="koffeekart_hp_hero_02.jpg" crc="155310325" ref="index"/>
    <file name="koffeekart_hp_hero_03.jpg" crc="3786955674" ref="index"/>
    <file name="koffeekart_hp_hero_04.jpg" crc="3970340272" ref="index"/>
    <file name="koffeekart_hp_hero_06.jpg" crc="400272648" ref="index"/>
    <file name="koffeekart_hp_hero_07.jpg" crc="3900641835" ref="index"/>
    <file name="loading.gif" crc="3815509949" ref="index:orgins"/>
    <file name="dailydrip.png" crc="371345997" ref="index"/>
    <file name="cloud-2.png" crc="4035804219" ref="index"/>
    <file name="cloud-1.png" crc="4044825168" ref="index"/>
    <file name="footer-zag.png" crc="3898363737" ref="index:the-koffee:kart-map:about:contact:preparation:orgins:confirmation"/>
    <file name="the-koffee-favicon.ico" crc="3814137969" ref="the-koffee"/>
    <file name="logo-u10507.png" crc="3919950060" ref="the-koffee:kart-map:about:contact:preparation:orgins:confirmation"/>
    <file name="top-nav-u137.png" crc="4277562052" ref="the-koffee:kart-map:about:contact:preparation:orgins:confirmation"/>
    <file name="head-thekoffee.png" crc="109657473" ref="the-koffee"/>
    <file name="02origins140x105.jpg" crc="3870522256" ref="the-koffee"/>
    <file name="acc-blue.png" crc="69255320" ref="the-koffee"/>
    <file name="acc-green.png" crc="4293714909" ref="the-koffee"/>
    <file name="kart-map-favicon.ico" crc="124002168" ref="kart-map"/>
    <file name="head-kartmap.png" crc="4232797748" ref="kart-map"/>
    <file name="mapfindus.png" crc="4259430994" ref="kart-map"/>
    <file name="master-favicon.ico" crc="55766034" ref="about"/>
    <file name="head-about.png" crc="4125023617" ref="about"/>
    <file name="thebean.png" crc="351999666" ref="about:orgins:confirmation"/>
    <file name="meetkevin.jpg" crc="3772840418" ref="about"/>
    <file name="contact-favicon.ico" crc="124002168" ref="contact"/>
    <file name="head-contact.png" crc="3861874093" ref="contact"/>
    <file name="head-getsocial.png" crc="37561020" ref="contact"/>
    <file name="ico-foursquare.png" crc="3957235089" ref="contact"/>
    <file name="ico-linkedin.png" crc="415005269" ref="contact"/>
    <file name="ico-twitter.png" crc="241617674" ref="contact"/>
    <file name="ico-yelp.png" crc="4120304028" ref="contact"/>
    <file name="head-prep.png" crc="180909968" ref="preparation"/>
    <file name="prep-yellow.png" crc="23052657" ref="preparation"/>
    <file name="tile-dash.png" crc="453849043" ref="preparation"/>
    <file name="prep01grindem.png" crc="90233041" ref="preparation"/>
    <file name="prep02fillerup.png" crc="4039890081" ref="preparation"/>
    <file name="prep03gettingwarmer.png" crc="21256735" ref="preparation"/>
    <file name="prep04dripdrip.png" crc="40520434" ref="preparation"/>
    <file name="prep05yumyum.png" crc="360019377" ref="preparation"/>
    <file name="prep00base.png" crc="169193827" ref="preparation"/>
    <file name="prep-blue.png" crc="3862096621" ref="preparation"/>
    <file name="prep-green.png" crc="247853650" ref="preparation"/>
    <file name="orgins-favicon.ico" crc="3814137969" ref="orgins"/>
    <file name="head-origins.png" crc="4093579841" ref="orgins"/>
    <file name="01origins.jpg" crc="4245079006" ref="orgins"/>
    <file name="02origins.jpg" crc="3999270139" ref="orgins"/>
    <file name="03origins.jpg" crc="4248366096" ref="orgins"/>
    <file name="05origins.jpg" crc="4004587983" ref="orgins"/>
    <file name="04origins.jpg" crc="326848909" ref="orgins"/>
    <file name="01origins109x82.jpg" crc="4096871115" ref="orgins"/>
    <file name="02origins109x82.jpg" crc="4187420642" ref="orgins"/>
    <file name="03origins109x82.jpg" crc="505666583" ref="orgins"/>
    <file name="05origins109x82.jpg" crc="3935084827" ref="orgins"/>
    <file name="04origins109x82.jpg" crc="72794824" ref="orgins"/>
    <file name="btn-previous.png" crc="3910238398" ref="orgins"/>
    <file name="btn-next.png" crc="384732555" ref="orgins"/>
    <file name="confirmation-favicon.ico" crc="124002168" ref="confirmation"/>
    <file name="head-submission.png" crc="4287661550" ref="confirmation"/>
  </folder>
  <file name="index.html" crc="3842227553" mt="1381320768312"/>
  <file name="the-koffee.html" crc="516332126" mt="1381320758421"/>
  <file name="kart-map.html" crc="383718455" mt="1381320758437"/>
  <file name="about.html" crc="4042173637" mt="1381320758437"/>
  <file name="contact.html" crc="4027828887" mt="1381320758453"/>
  <file name="preparation.html" crc="382850726" mt="1381320758453"/>
  <file name="orgins.html" crc="4167347987" mt="1381320758468"/>
  <file name="confirmation.html" crc="3997579790" mt="1381320758468"/>
</manifest>